BlueWhale3-3.31.3.data/data/share/help/en/orange3/htmlhelp/.buildinfo
BlueWhale3-3.31.3.data/data/share/help/en/orange3/htmlhelp/genindex.html
BlueWhale3-3.31.3.data/data/share/help/en/orange3/htmlhelp/index.html
BlueWhale3-3.31.3.data/data/share/help/en/orange3/htmlhelp/_images/AdaBoost-classification.png
BlueWhale3-3.31.3.data/data/share/help/en/orange3/htmlhelp/_images/AdaBoost-regression.png
BlueWhale3-3.31.3.data/data/share/help/en/orange3/htmlhelp/_images/AdaBoost-stamped.png
BlueWhale3-3.31.3.data/data/share/help/en/orange3/htmlhelp/_images/AggregateColumns-Example.png
BlueWhale3-3.31.3.data/data/share/help/en/orange3/htmlhelp/_images/AggregateColumns.png
BlueWhale3-3.31.3.data/data/share/help/en/orange3/htmlhelp/_images/ApplyDomain-Example.png
BlueWhale3-3.31.3.data/data/share/help/en/orange3/htmlhelp/_images/ApplyDomain.png
BlueWhale3-3.31.3.data/data/share/help/en/orange3/htmlhelp/_images/Bar-Plot-Example.png
BlueWhale3-3.31.3.data/data/share/help/en/orange3/htmlhelp/_images/Bar-Plot-stamped.png
BlueWhale3-3.31.3.data/data/share/help/en/orange3/htmlhelp/_images/BoxPlot-Continuous-small.png
BlueWhale3-3.31.3.data/data/share/help/en/orange3/htmlhelp/_images/BoxPlot-Continuous-stamped.png
BlueWhale3-3.31.3.data/data/share/help/en/orange3/htmlhelp/_images/BoxPlot-Continuous.png
BlueWhale3-3.31.3.data/data/share/help/en/orange3/htmlhelp/_images/BoxPlot-Discrete.png
BlueWhale3-3.31.3.data/data/share/help/en/orange3/htmlhelp/_images/BoxPlot-Example1.png
BlueWhale3-3.31.3.data/data/share/help/en/orange3/htmlhelp/_images/BoxPlot-Example2.png
BlueWhale3-3.31.3.data/data/share/help/en/orange3/htmlhelp/_images/CN2-Viewer-Example1.png
BlueWhale3-3.31.3.data/data/share/help/en/orange3/htmlhelp/_images/CN2-classification.png
BlueWhale3-3.31.3.data/data/share/help/en/orange3/htmlhelp/_images/CN2-stamped.png
BlueWhale3-3.31.3.data/data/share/help/en/orange3/htmlhelp/_images/CN2-visualize.png
BlueWhale3-3.31.3.dist-info/LICENSE
BlueWhale3-3.31.3.dist-info/METADATA
BlueWhale3-3.31.3.dist-info/WHEEL
BlueWhale3-3.31.3.dist-info/entry_points.txt
BlueWhale3-3.31.3.dist-info/top_level.txt
BlueWhale3-3.31.3.dist-info/RECORD
