Metadata-Version: 2.1
Name: BlueWhale3
Version: 3.31.3
Summary: 蓝鲸，一个基于组件的数据挖掘框架。
Home-page: https://bw.dashenglab.com/
Author: 大圣实验楼
Author-email: dashenglab@163.com
License: GPLv3+
Keywords: data mining,machine learning,artificial intelligence
Platform: UNKNOWN
Classifier: Development Status :: 4 - Beta
Classifier: Environment :: X11 Applications :: Qt
Classifier: Environment :: Console
Classifier: Environment :: Plugins
Classifier: Programming Language :: Python
Classifier: License :: OSI Approved :: GNU General Public License v3 or later (GPLv3+)
Classifier: Operating System :: POSIX
Classifier: Operating System :: Microsoft :: Windows
Classifier: Topic :: Scientific/Engineering :: Artificial Intelligence
Classifier: Topic :: Scientific/Engineering :: Visualization
Classifier: Topic :: Software Development :: Libraries :: Python Modules
Classifier: Intended Audience :: Education
Classifier: Intended Audience :: Science/Research
Classifier: Intended Audience :: Developers
License-File: LICENSE
Requires-Dist: AnyQt (>=0.0.11)
Requires-Dist: BlueWhale3-BlueWhale (>=0.0.52)
Requires-Dist: PyQt5 (!=5.15.1,>=5.12)
Requires-Dist: PyQtWebEngine (>=5.12)
Requires-Dist: baycomp (>=1.0.2)
Requires-Dist: bluewhale-canvas-core (<0.2a,>=0.1.25)
Requires-Dist: bluewhale-widget-base (>=4.15.1)
Requires-Dist: bottleneck (>=1.0.0)
Requires-Dist: chardet (>=3.0.2)
Requires-Dist: httpx (<0.20,>=0.14.0)
Requires-Dist: joblib (>=0.9.4)
Requires-Dist: keyring
Requires-Dist: keyrings.alt
Requires-Dist: matplotlib (>=2.0.0)
Requires-Dist: networkx
Requires-Dist: numpy-groupies
Requires-Dist: numpy (>=1.16.0)
Requires-Dist: openTSNE (>=0.6.1)
Requires-Dist: openpyxl
Requires-Dist: pandas (>=1.0.0)
Requires-Dist: pip (>=9.0)
Requires-Dist: pygments (>=2.8.0)
Requires-Dist: pyqtgraph (>=0.11.1)
Requires-Dist: python-i18n
Requires-Dist: python-louvain (>=0.13)
Requires-Dist: pyyaml
Requires-Dist: qtconsole (>=4.7.2)
Requires-Dist: requests
Requires-Dist: scikit-learn (!=1.0.0,>0.23.0)
Requires-Dist: scipy (>=0.16.1)
Requires-Dist: serverfiles
Requires-Dist: setuptools (>=36.3)
Requires-Dist: xlrd (>=0.9.2)
Requires-Dist: xlsxwriter
